ephor_server_ti_client/__init__.py
ephor_server_ti_client/api_client.py
ephor_server_ti_client/api_response.py
ephor_server_ti_client/configuration.py
ephor_server_ti_client/exceptions.py
ephor_server_ti_client/py.typed
ephor_server_ti_client/rest.py
ephor_server_ti_client/api/__init__.py
ephor_server_ti_client/api/account_api.py
ephor_server_ti_client/api/artifacts_api.py
ephor_server_ti_client/api/background_services_api.py
ephor_server_ti_client/api/channels_api.py
ephor_server_ti_client/api/conversations_api.py
ephor_server_ti_client/api/crawl_api.py
ephor_server_ti_client/api/default_api.py
ephor_server_ti_client/api/feedback_api.py
ephor_server_ti_client/api/generate_api.py
ephor_server_ti_client/api/ingest_api.py
ephor_server_ti_client/api/interact_api.py
ephor_server_ti_client/api/library_api.py
ephor_server_ti_client/api/projects_api.py
ephor_server_ti_client/api/read_ai_api.py
ephor_server_ti_client/api/recommendation_api.py
ephor_server_ti_client/api/redis_api.py
ephor_server_ti_client/api/retrieve_api.py
ephor_server_ti_client/api/search_api.py
ephor_server_ti_client/api/second_brain_api.py
ephor_server_ti_client/api/tasks_api.py
ephor_server_ti_client/api/text_api.py
ephor_server_ti_client/models/__init__.py
ephor_server_ti_client/models/account.py
ephor_server_ti_client/models/account_id_response.py
ephor_server_ti_client/models/artifact.py
ephor_server_ti_client/models/attachment.py
ephor_server_ti_client/models/attachment_download_response.py
ephor_server_ti_client/models/attachment_upload_request.py
ephor_server_ti_client/models/attachment_upload_response.py
ephor_server_ti_client/models/auth_response.py
ephor_server_ti_client/models/authorize_google_response.py
ephor_server_ti_client/models/body_add_webcrawling_request_api_v1_crawl_new_post.py
ephor_server_ti_client/models/body_export_data_api_v1_projects_project_id_export_post.py
ephor_server_ti_client/models/bot_dispatch_request.py
ephor_server_ti_client/models/bot_stop_request.py
ephor_server_ti_client-1.0.0.dist-info/METADATA
ephor_server_ti_client-1.0.0.dist-info/WHEEL
ephor_server_ti_client-1.0.0.dist-info/top_level.txt
ephor_server_ti_client-1.0.0.dist-info/RECORD
